tokenstream/__init__.py
tokenstream/error.py
tokenstream/location.py
tokenstream/py.typed
tokenstream/stream.py
tokenstream/token.py
tokenstream-1.6.0.dist-info/LICENSE
tokenstream-1.6.0.dist-info/METADATA
tokenstream-1.6.0.dist-info/WHEEL
tokenstream-1.6.0.dist-info/RECORD
