Metadata-Version: 2.1
Name: tokenstream
Version: 1.6.0
Summary: A versatile token stream for handwritten parsers
Home-page: https://github.com/vberlier/tokenstream
License: MIT
Keywords: parsing,tokenizer,lexer,recursive-descent-parser,token-stream
Author: Valentin Berlier
Author-email: berlier.v@gmail.com
Requires-Python: >=3.10,<4.0
Classifier: License :: OSI Approved :: MIT License
Classifier: Programming Language :: Python :: 3
Classifier: Programming Language :: Python :: 3.10
Classifier: Programming Language :: Python :: 3.11
Project-URL: Documentation, https://github.com/vberlier/tokenstream
Project-URL: Repository, https://github.com/vberlier/tokenstream
